faceid_dev/CHANGELOG.md
faceid_dev/Makefile
faceid_dev/__init__.cpython-38-darwin.so
faceid_dev/__main__.cpython-38-darwin.so
faceid_dev/events/__init__.cpython-38-darwin.so
faceid_dev/events/event_producer.cpython-38-darwin.so
faceid_dev/events/event_receiver.cpython-38-darwin.so
faceid_dev/logger/__init__.cpython-38-darwin.so
faceid_dev/logger/logger_helper.cpython-38-darwin.so
faceid_dev/logger/test.cpython-38-darwin.so
faceid_dev/logger/test2.cpython-38-darwin.so
faceid_dev/ratelimiter/__init__.cpython-38-darwin.so
faceid_dev/ratelimiter/depends.cpython-38-darwin.so
faceid_dev/vector_similarity/__init__.cpython-38-darwin.so
faceid_dev/vector_similarity/v1/__init__.cpython-38-darwin.so
faceid_dev/vector_similarity/v1/power.cpython-38-darwin.so
faceid_dev/workflow/__init__.cpython-38-darwin.so
faceid_dev/workflow/workflow_helper.cpython-38-darwin.so
faceid_dev-0.0.4.dist-info/entry_points.txt
faceid_dev-0.0.4.dist-info/WHEEL
faceid_dev-0.0.4.dist-info/METADATA
faceid_dev-0.0.4.dist-info/RECORD
